pasahitzak/__init__.py
pasahitzak/password.py
pasahitzak-0.0.1.dist-info/LICENSE.txt
pasahitzak-0.0.1.dist-info/METADATA
pasahitzak-0.0.1.dist-info/WHEEL
pasahitzak-0.0.1.dist-info/top_level.txt
pasahitzak-0.0.1.dist-info/RECORD
