Metadata-Version: 2.1
Name: pasahitzak
Version: 0.0.1
Summary: A package to deal with passwords
Author-email: Eneko Renteria <eneko.renteria@alumni.mondragon.edu>
Project-URL: Homepage, https://github.com/mariaepel/PasswordManager
Project-URL: Bug Tracker, https://github.com/mariaepel/PasswordManager/issues
Classifier: Programming Language :: Python :: 3
Classifier: License :: OSI Approved :: MIT License
Classifier: Operating System :: OS Independent
Requires-Python: >=3.7
License-File: LICENSE.txt
